airQ/__init__.py
airQ/app.py
airQ/config.json
airQ/util.py
airQ/model/data.py
airQ/model/pollutant.py
airQ/model/station.py
airQ/model/url.py
airQ-0.3.3.dist-info/entry_points.txt
airQ-0.3.3.dist-info/LICENSE
airQ-0.3.3.dist-info/WHEEL
airQ-0.3.3.dist-info/METADATA
airQ-0.3.3.dist-info/RECORD
