Metadata-Version: 2.1
Name: airQ
Version: 0.3.3
Summary: airQ - Air Quality monitoring data ( for India ) collection system, written in Python3.
Home-page: https://github.com/itzmeanjan/airQ
License: UNKNOWN
Author: Anjan Roy
Author-email: anjanroy@yandex.com
Requires-Python: >=3.7
Classifier: License :: OSI Approved :: MIT License
Requires-Dist: flit ; extra == "dev"
Provides-Extra: dev
